tinytune/__init__.py
tinytune/llmcontext.py
tinytune/pipeline.py
tinytune/prompt.py
tinytune/tool.py
tinytune/contexts/gptcontext.py
tinytune/util/__init__.py
tinytune/util/prompt.py
tinytune-0.0.9.dist-info/METADATA
tinytune-0.0.9.dist-info/WHEEL
tinytune-0.0.9.dist-info/licenses/LICENSE
tinytune-0.0.9.dist-info/RECORD
