Metadata-Version: 2.4
Name: tinytune
Version: 0.0.9
Summary: A simple prompt tuning library for LLMs
Project-URL: Github, https://github.com/rishit-singh/tinytune
Author-email: Rishit Singh <rsrishitsingh@gmail.com>
License-File: LICENSE
Classifier: License :: OSI Approved :: MIT License
Classifier: Operating System :: OS Independent
Classifier: Programming Language :: Python :: 3
Requires-Python: >=3.12
